README.rst
setup.cfg
setup.py
nelpy/__init__.py
nelpy/all.py
nelpy/decoders.py
nelpy/decoding.py
nelpy/estimators.py
nelpy/estimators2.py
nelpy/filtering.py
nelpy/formatters.py
nelpy/hmmutils.py
nelpy/homography.py
nelpy/ipynb.py
nelpy/min.py
nelpy/preprocessing.py
nelpy/scoring.py
nelpy/temp.py
nelpy/utils.py
nelpy/version.py
nelpy.egg-info/PKG-INFO
nelpy.egg-info/SOURCES.txt
nelpy.egg-info/dependency_links.txt
nelpy.egg-info/requires.txt
nelpy.egg-info/top_level.txt
nelpy/analysis/__init__.py
nelpy/analysis/ergodic.py
nelpy/analysis/hmm_sparsity.py
nelpy/analysis/replay.py
nelpy/auxiliary/__init__.py
nelpy/auxiliary/_animal.py
nelpy/auxiliary/_experiment.py
nelpy/auxiliary/_imu.py
nelpy/auxiliary/_position.py
nelpy/auxiliary/_results.py
nelpy/auxiliary/_session.py
nelpy/auxiliary/_tuningcurve.py
nelpy/core/__init__.py
nelpy/core/_analogsignalarray.py
nelpy/core/_coordinates.py
nelpy/core/_eventarray.py
nelpy/core/_grouping.py
nelpy/core/_intervalarray.py
nelpy/core/_valeventarray.py
nelpy/examples/__init__.py
nelpy/examples/_utils.py
nelpy/io/__init__.py
nelpy/io/brian.py
nelpy/io/hc11.py
nelpy/io/hc18.py
nelpy/io/hc3.py
nelpy/io/matlab.py
nelpy/io/miniscopy.py
nelpy/io/neo.py
nelpy/io/neuralynx.py
nelpy/plotting/__init__.py
nelpy/plotting/colormaps.py
nelpy/plotting/colors.py
nelpy/plotting/core.py
nelpy/plotting/decoding.py
nelpy/plotting/graph.py
nelpy/plotting/helpers.py
nelpy/plotting/miscplot.py
nelpy/plotting/palettes.py
nelpy/plotting/rcmod.py
nelpy/plotting/scalebar.py
nelpy/plotting/utils.py
nelpy/utils_/__init__.py
nelpy/utils_/decorators.py
nelpy/utils_/metrics.py
nelpy/utils_/temp.py