Metadata-Version: 1.1
Name: nelpy
Version: 0.2.1
Summary: Neuroelectrophysiology object model and data analysis in Python.
Home-page: https://github.com/nelpy/nelpy/
Author: Etienne Ackermann
Author-email: era3@rice.edu
License: MIT License
Download-URL: https://github.com/nelpy/nelpy/tarball/0.2.1
Keywords: electrophysiology neuroscience data analysis
Platform: any
